{
    "author": ["psykzz"],
    "name": "VideoDownloader",
    "short": "Download videos from DMs for bot owner",
    "description": "Downloads videos from YouTube, TikTok, and Instagram when sent via DM by the bot owner. Uses yt-dlp to download videos and sends them back as Discord attachments. Requires ffmpeg to be installed on the system for merging video and audio streams.",
    "permissions": ["Send Messages", "Attach Files"],
    "requirements": ["yt-dlp>=2023.1.1"],
    "system_dependencies": ["ffmpeg"],
    "tags": [
        "Video",
        "Download",
        "YouTube",
        "TikTok",
        "Instagram",
        "Owner"
    ]
}
